seedance2_ai/__init__.py
seedance_2-0.1.0.dist-info/METADATA
seedance_2-0.1.0.dist-info/WHEEL
seedance_2-0.1.0.dist-info/licenses/LICENSE
seedance_2-0.1.0.dist-info/RECORD
