Metadata-Version: 2.4
Name: seedance-2
Version: 0.1.0
Summary: Seedance 2 - Next-generation AI platform with powerful capabilities
Project-URL: Homepage, https://seedance-2.net
Project-URL: Website, https://seedance-2.net
License: MIT
License-File: LICENSE
Keywords: ai,artificial-intelligence,seedance
Requires-Python: >=3.9
